Topsis_Chavvi
